{
  "members": [
    {
      "id": "member-1",
      "name": "林修賢",
      "photo": "images/members/林修賢.jpg",
      "industry": "醫療輔具",
      "category": "健康美麗",
      "company": "益立福生物科技有限公司",
      "position": "董事長",
      "title": "董事長 - 益立福生物科技有限公司",
      "shortIntro": "醫療輔具 找修賢 從頭到腳 最專業",
      "fullIntro": "我是林修賢，專注於醫療輔具。\n醫療輔具 找修賢 從頭到腳 最專業\n\n【理想引薦對象】\n骨科、復健科醫師，醫院及診所\n\n【聯絡方式】\n0905-510-604 eeniusjk@gmail.com",
      "links": [
        {
          "type": "facebook",
          "url": "#",
          "icon": "facebook"
        },
        {
          "type": "line",
          "url": "#",
          "icon": "line"
        },
        {
          "type": "website",
          "url": "#",
          "icon": "website"
        }
      ],
      "services": [
        "客製化矯正鞋墊",
        "各類醫療輔具"
      ],
      "hashtags": [
        "#醫療輔具業",
        "#林修賢",
        "#BNI長輝白金分會"
      ],
      "createdAt": "2025-11-26T01:02:38.842Z",
      "updatedAt": "2025-12-13T16:55:59.174Z",
      "pinHash": "e286648cc9b96588da67f1b8100a650b96850881c79cb777dc88877a3ccfb96f",
      "editCount": 2
    },
    {
      "id": "member-2",
      "name": "吳介輝",
      "photo": "images/members/吳介輝.jpg",
      "industry": "人壽保險",
      "category": "健康美麗",
      "company": "南山人壽 重盛通訊處",
      "position": "董事長",
      "title": "董事長 - 南山人壽 重盛通訊處",
      "shortIntro": "長照理財 找介輝 讓你生命 更光輝",
      "fullIntro": "我是吳介輝，專注於人壽保險。\n長照理財 找介輝 讓你生命 更光輝\n\n【理想引薦對象】\n骨/復健科醫師、中醫師 牙醫師、長照機構\n\n【聯絡方式】\n0911-602-709 michaelwu7676@gmail.com",
      "links": [
        {
          "type": "facebook",
          "url": "#",
          "icon": "facebook"
        },
        {
          "type": "line",
          "url": "#",
          "icon": "line"
        },
        {
          "type": "website",
          "url": "#",
          "icon": "website"
        }
      ],
      "services": [
        "醫療",
        "意外",
        "儲蓄",
        "長照規劃"
      ],
      "hashtags": [
        "#人壽保險業",
        "#吳介輝",
        "#BNI長輝白金分會"
      ],
      "createdAt": "2025-11-26T01:02:38.842Z",
      "updatedAt": "2025-12-13T16:55:59.175Z",
      "pinHash": "e286648cc9b96588da67f1b8100a650b96850881c79cb777dc88877a3ccfb96f",
      "editCount": 2
    },
    {
      "id": "member-3",
      "name": "郭家宏",
      "photo": "images/members/郭家宏.jpg",
      "industry": "甜品外燴",
      "category": "美食餐飲",
      "company": "一百分股份有限公司",
      "position": "董事長",
      "title": "董事長 - 一百分股份有限公司",
      "shortIntro": "活動餐點 甜饗派 一站服務 不用煩",
      "fullIntro": "我是郭家宏，專注於甜品外燴。\n活動餐點 甜饗派 一站服務 不用煩\n\n【理想引薦對象】\n活動企劃公司/行銷公司/公關公司/婚禮企劃公司\n\n【聯絡方式】\n0912-618-501 egg100daan@gmail.com",
      "links": [
        {
          "type": "facebook",
          "url": "#",
          "icon": "facebook"
        },
        {
          "type": "line",
          "url": "#",
          "icon": "line"
        },
        {
          "type": "website",
          "url": "#",
          "icon": "website"
        }
      ],
      "services": [
        "春酒尾牙Candy Bar/活動下午茶/會議餐盒點心"
      ],
      "hashtags": [
        "#無麩質雞蛋糕",
        "#郭家宏",
        "#BNI長輝白金分會"
      ],
      "createdAt": "2025-11-26T01:02:38.843Z",
      "updatedAt": "2025-12-13T16:55:59.175Z",
      "pinHash": "e286648cc9b96588da67f1b8100a650b96850881c79cb777dc88877a3ccfb96f",
      "editCount": 2
    },
    {
      "id": "member-4",
      "name": "江沛璇",
      "photo": "images/members/江沛璇.jpg",
      "industry": "營養保健",
      "category": "健康美麗",
      "company": "Amway安麗",
      "position": "董事長",
      "title": "董事長 - Amway安麗",
      "shortIntro": "草本養生 找沛璇 美好生活 逐笑顏",
      "fullIntro": "我是江沛璇，專注於營養保健。\n草本養生 找沛璇 美好生活 逐笑顏\n\n【理想引薦對象】\n心理諮商、中醫師、家醫科醫師\n\n【聯絡方式】\n0939-664-562 ilchiang@yahoo.com",
      "links": [
        {
          "type": "facebook",
          "url": "#",
          "icon": "facebook"
        },
        {
          "type": "line",
          "url": "#",
          "icon": "line"
        },
        {
          "type": "website",
          "url": "#",
          "icon": "website"
        }
      ],
      "services": [
        "營養保健品",
        "營養早餐",
        "健管計劃"
      ],
      "hashtags": [
        "#營養保健業",
        "#江沛璇",
        "#BNI長輝白金分會"
      ],
      "createdAt": "2025-11-26T01:02:38.842Z",
      "updatedAt": "2025-12-13T16:55:59.175Z",
      "pinHash": "e286648cc9b96588da67f1b8100a650b96850881c79cb777dc88877a3ccfb96f",
      "editCount": 2
    },
    {
      "id": "member-5",
      "name": "王執定",
      "photo": "images/members/王執定.jpg",
      "industry": "信託規劃顧問",
      "category": "企業顧問",
      "company": "問大師家族辦公室",
      "position": "董事長",
      "title": "董事長 - 問大師家族辦公室",
      "shortIntro": "信託規劃 找執定 無憂無慮 心安定",
      "fullIntro": "我是王執定，專注於信託規劃顧問。\n信託規劃 找執定 無憂無慮 心安定\n\n【理想引薦對象】\n長照、銀髮機構業者\n\n【聯絡方式】\n0927-860-882 garfiwang@gmail.com",
      "links": [
        {
          "type": "facebook",
          "url": "#",
          "icon": "facebook"
        },
        {
          "type": "line",
          "url": "#",
          "icon": "line"
        },
        {
          "type": "website",
          "url": "#",
          "icon": "website"
        }
      ],
      "services": [
        "信託規劃",
        "財產規劃"
      ],
      "hashtags": [
        "#信託規劃顧問",
        "#王執定",
        "#BNI長輝白金分會"
      ],
      "createdAt": "2025-11-26T01:02:38.842Z",
      "updatedAt": "2025-12-13T16:55:59.175Z",
      "pinHash": "e286648cc9b96588da67f1b8100a650b96850881c79cb777dc88877a3ccfb96f",
      "editCount": 2
    },
    {
      "id": "member-6",
      "name": "王冠勛",
      "photo": "images/members/王冠勛.jpg",
      "industry": "燈具照明",
      "category": "工程裝修",
      "company": "長輝照明科技有限公司",
      "position": "董事長",
      "title": "董事長 - 長輝照明科技有限公司",
      "shortIntro": "生活照明 找冠勛 人生光明 得冠軍",
      "fullIntro": "我是王冠勛，專注於燈具照明。\n生活照明 找冠勛 人生光明 得冠軍\n\n【理想引薦對象】\n室內設計師、營造廠主任、水電工程包商\n\n【聯絡方式】\n0911-205-224 line ID:ederwang",
      "links": [
        {
          "type": "facebook",
          "url": "#",
          "icon": "facebook"
        },
        {
          "type": "line",
          "url": "#",
          "icon": "line"
        },
        {
          "type": "website",
          "url": "#",
          "icon": "website"
        }
      ],
      "services": [
        "照明燈具批發",
        "規劃",
        "客製化訂做"
      ],
      "hashtags": [
        "#燈具照明",
        "#王冠勛",
        "#BNI長輝白金分會"
      ],
      "createdAt": "2025-11-26T01:02:38.842Z",
      "updatedAt": "2025-12-13T16:55:59.175Z",
      "pinHash": "e286648cc9b96588da67f1b8100a650b96850881c79cb777dc88877a3ccfb96f",
      "editCount": 2
    },
    {
      "id": "member-7",
      "name": "何昇軒",
      "photo": "images/members/何昇軒.jpg",
      "industry": "律師",
      "category": "企業顧問",
      "company": "德恭法律事務所",
      "position": "董事長",
      "title": "董事長 - 德恭法律事務所",
      "shortIntro": "訴訟經驗 最齊全 法律諮詢 何昇軒",
      "fullIntro": "我是何昇軒，專注於律師。\n訴訟經驗 最齊全 法律諮詢 何昇軒\n\n【理想引薦對象】\n命理師、銀行理專\n\n【聯絡方式】\n0985-697-791 ntpuho@gmail.com",
      "links": [
        {
          "type": "facebook",
          "url": "#",
          "icon": "facebook"
        },
        {
          "type": "line",
          "url": "#",
          "icon": "line"
        },
        {
          "type": "website",
          "url": "#",
          "icon": "website"
        }
      ],
      "services": [
        "訴訟",
        "法律諮詢服務"
      ],
      "hashtags": [
        "#律師",
        "#何昇軒",
        "#BNI長輝白金分會"
      ],
      "createdAt": "2025-11-26T01:02:38.835Z",
      "updatedAt": "2025-12-13T16:55:59.175Z",
      "pinHash": "e286648cc9b96588da67f1b8100a650b96850881c79cb777dc88877a3ccfb96f",
      "editCount": 2
    },
    {
      "id": "member-8",
      "name": "杜宗樺",
      "photo": "images/members/杜宗樺.jpg",
      "industry": "商空設計",
      "category": "工程裝修",
      "company": "提芙設計工程有限公司",
      "position": "董事長",
      "title": "董事長 - 提芙設計工程有限公司",
      "shortIntro": "風格國際 又獨特 商空設計 找杜哥",
      "fullIntro": "我是杜宗樺，專注於商空設計。\n風格國際 又獨特 商空設計 找杜哥\n\n【理想引薦對象】\n星巴克、星巴克、星巴克\n\n【聯絡方式】\n0937-666-877 design@e-deva.com.tw",
      "links": [
        {
          "type": "facebook",
          "url": "#",
          "icon": "facebook"
        },
        {
          "type": "line",
          "url": "#",
          "icon": "line"
        },
        {
          "type": "website",
          "url": "#",
          "icon": "website"
        }
      ],
      "services": [
        "連鎖餐飲",
        "汽車展覽"
      ],
      "hashtags": [
        "#商空設計",
        "#杜宗樺",
        "#BNI長輝白金分會"
      ],
      "createdAt": "2025-11-26T01:02:38.842Z",
      "updatedAt": "2025-12-13T16:55:59.175Z",
      "pinHash": "e286648cc9b96588da67f1b8100a650b96850881c79cb777dc88877a3ccfb96f",
      "editCount": 2
    },
    {
      "id": "member-9",
      "name": "賴瑋弘",
      "photo": "images/members/賴瑋弘.jpg",
      "industry": "物理治療師",
      "category": "健康美麗",
      "company": "樂霖物理治療所",
      "position": "董事長",
      "title": "董事長 - 樂霖物理治療所",
      "shortIntro": "身體痠痛 找瑋弘 讓你健康 氣勢虹",
      "fullIntro": "我是賴瑋弘，專注於物理治療師。\n身體痠痛 找瑋弘 讓你健康 氣勢虹\n\n【理想引薦對象】\n骨科及復健科醫師、健身教練\n\n【聯絡方式】\n0921-345-753 pe7256@gmail.com",
      "links": [
        {
          "type": "facebook",
          "url": "#",
          "icon": "facebook"
        },
        {
          "type": "line",
          "url": "#",
          "icon": "line"
        },
        {
          "type": "website",
          "url": "#",
          "icon": "website"
        }
      ],
      "services": [
        "疼痛解除",
        "徒手治療",
        "運動治療"
      ],
      "hashtags": [
        "#物理治療師",
        "#賴瑋弘",
        "#BNI長輝白金分會"
      ],
      "createdAt": "2025-11-26T01:02:38.843Z",
      "updatedAt": "2025-12-13T16:55:59.175Z",
      "pinHash": "e286648cc9b96588da67f1b8100a650b96850881c79cb777dc88877a3ccfb96f",
      "editCount": 2
    },
    {
      "id": "member-10",
      "name": "江學洋",
      "photo": "images/members/江學洋.jpg",
      "industry": "品牌設計",
      "category": "企業顧問",
      "company": "溫體氣流廣告製作有限公司",
      "position": "董事長",
      "title": "董事長 - 溫體氣流廣告製作有限公司",
      "shortIntro": "品牌設計 找學洋 業績提升 喜洋洋",
      "fullIntro": "我是江學洋，專注於品牌設計。\n品牌設計 找學洋 業績提升 喜洋洋\n\n【理想引薦對象】\n傳產二代接班轉型想做品牌、連鎖餐飲品牌打理、新開店面品牌\n\n【聯絡方式】\n0986-921-263",
      "links": [
        {
          "type": "facebook",
          "url": "#",
          "icon": "facebook"
        },
        {
          "type": "line",
          "url": "#",
          "icon": "line"
        },
        {
          "type": "website",
          "url": "#",
          "icon": "website"
        }
      ],
      "services": [
        "用品牌識別幫你說一個好故事"
      ],
      "hashtags": [
        "#品牌設計",
        "#江學洋",
        "#BNI長輝白金分會"
      ],
      "createdAt": "2025-11-26T01:02:38.842Z",
      "updatedAt": "2025-12-13T16:55:59.175Z",
      "pinHash": "e286648cc9b96588da67f1b8100a650b96850881c79cb777dc88877a3ccfb96f",
      "editCount": 2
    },
    {
      "id": "member-11",
      "name": "孫成育",
      "photoPosition": "top",
      "photo": "images/members/孫成育.jpg",
      "industry": "禮贈品",
      "category": "企業行銷",
      "company": "和朝創意開發有限公司",
      "position": "董事長",
      "title": "董事長 - 和朝創意開發有限公司",
      "shortIntro": "贈品商品找Johnson 行銷效益 有保證",
      "fullIntro": "我是孫成育，專注於禮贈品。\n贈品商品找Johnson 行銷效益 有保證\n\n【理想引薦對象】\n品牌策略、廣告企劃、展覽規劃、線上線下整合行銷\n\n【聯絡方式】\n0935-009-651 johnson@harvestnest.com",
      "links": [
        {
          "type": "facebook",
          "url": "#",
          "icon": "facebook"
        },
        {
          "type": "line",
          "url": "#",
          "icon": "line"
        },
        {
          "type": "website",
          "url": "#",
          "icon": "website"
        }
      ],
      "services": [
        "企業禮贈品",
        "文創個性商品創意商品開發",
        "包袋類製作"
      ],
      "hashtags": [
        "#禮贈品",
        "#孫成育",
        "#BNI長輝白金分會"
      ],
      "createdAt": "2025-11-26T01:02:38.842Z",
      "updatedAt": "2025-12-13T16:55:59.175Z",
      "pinHash": "e286648cc9b96588da67f1b8100a650b96850881c79cb777dc88877a3ccfb96f",
      "editCount": 2
    },
    {
      "id": "member-13",
      "name": "邱宇鴻",
      "photo": "images/members/邱宇鴻.jpg",
      "industry": "中小企業顧問",
      "category": "企業顧問",
      "company": "夢想成真資訊股份有限公司",
      "position": "董事長",
      "title": "董事長 - 夢想成真資訊股份有限公司",
      "shortIntro": "問題解決 全方位 省錢賺錢 邱宇鴻",
      "fullIntro": "我是邱宇鴻，專注於中小企業顧問。\n問題解決 全方位 省錢賺錢 邱宇鴻\n\n【理想引薦對象】\n新創中小企業、想開發電商網路企業 中小企業老闆(20人以下) 、傳產想經營網路電商、新創公司(剛創業諮詢)\n\n【聯絡方式】\n0989-018-852",
      "links": [
        {
          "type": "facebook",
          "url": "#",
          "icon": "facebook"
        },
        {
          "type": "line",
          "url": "#",
          "icon": "line"
        },
        {
          "type": "website",
          "url": "#",
          "icon": "website"
        }
      ],
      "services": [
        "電腦資訊網路解決"
      ],
      "hashtags": [
        "#中小企業顧問",
        "#邱宇鴻",
        "#BNI長輝白金分會"
      ],
      "createdAt": "2025-11-26T01:02:38.843Z",
      "updatedAt": "2025-12-13T16:55:59.175Z",
      "pinHash": "e286648cc9b96588da67f1b8100a650b96850881c79cb777dc88877a3ccfb96f",
      "editCount": 2
    },
    {
      "id": "member-14",
      "name": "廖俊瑋",
      "photo": "images/members/廖俊瑋.jpg",
      "industry": "會計師",
      "category": "企業顧問",
      "company": "宇雋會計師事務所",
      "position": "董事長",
      "title": "董事長 - 宇雋會計師事務所",
      "shortIntro": "會計稅務 找俊瑋 輕鬆省稅 最到位",
      "fullIntro": "我是廖俊瑋，專注於會計師。\n會計稅務 找俊瑋 輕鬆省稅 最到位\n\n【理想引薦對象】\n銀行企金、勞資顧問、移民公司、政府貸款或補助款 (文化部補助款申請或寫手)\n\n【聯絡方式】\n0916-246-263",
      "links": [
        {
          "type": "facebook",
          "url": "#",
          "icon": "facebook"
        },
        {
          "type": "line",
          "url": "#",
          "icon": "line"
        },
        {
          "type": "website",
          "url": "#",
          "icon": "website"
        }
      ],
      "services": [
        "帳務處理",
        "工商登記",
        "財稅簽證 工作簽證/居留"
      ],
      "hashtags": [
        "#會計師",
        "#廖俊瑋",
        "#BNI長輝白金分會"
      ],
      "createdAt": "2025-11-26T01:02:38.842Z",
      "updatedAt": "2025-12-13T16:55:59.175Z",
      "pinHash": "e286648cc9b96588da67f1b8100a650b96850881c79cb777dc88877a3ccfb96f",
      "editCount": 2
    },
    {
      "id": "member-17",
      "name": "陳育文",
      "photo": "images/members/陳育文.jpg",
      "industry": "住宅設計",
      "category": "工程裝修",
      "company": "亞罕室內設計事務所",
      "position": "董事長",
      "title": "董事長 - 亞罕室內設計事務所",
      "shortIntro": "住宅設計 找育文 老屋豪宅 樣樣能",
      "fullIntro": "我是陳育文，專注於住宅設計。\n住宅設計 找育文 老屋豪宅 樣樣能\n\n【理想引薦對象】\n房仲、代銷、危老鑑定師\n\n【聯絡方式】\n0921-293-160 vcaido2009@gmail.com",
      "links": [
        {
          "type": "facebook",
          "url": "#",
          "icon": "facebook"
        },
        {
          "type": "line",
          "url": "#",
          "icon": "line"
        },
        {
          "type": "website",
          "url": "#",
          "icon": "website"
        }
      ],
      "services": [
        "室內設計",
        "施工"
      ],
      "hashtags": [
        "#住宅設計",
        "#陳育文",
        "#BNI長輝白金分會"
      ],
      "createdAt": "2025-11-26T01:02:38.843Z",
      "updatedAt": "2025-12-13T16:55:59.175Z",
      "pinHash": "e286648cc9b96588da67f1b8100a650b96850881c79cb777dc88877a3ccfb96f",
      "editCount": 2
    },
    {
      "id": "member-18",
      "name": "李彥慶",
      "photo": "images/members/李彥慶.jpg",
      "industry": "專利商標",
      "category": "企業顧問",
      "company": "博拓國際智權集團",
      "position": "董事長",
      "title": "董事長 - 博拓國際智權集團",
      "shortIntro": "專利商標 找彥慶 博拓智權 保護您",
      "fullIntro": "我是李彥慶，專注於專利商標。\n專利商標 找彥慶 博拓智權 保護您\n\n【理想引薦對象】\n想要保護創意商品服務不受侵害或是避免侵權的企業\n\n【聯絡方式】\n0963-014-517 Daniel@piip.pro",
      "links": [
        {
          "type": "facebook",
          "url": "#",
          "icon": "facebook"
        },
        {
          "type": "line",
          "url": "#",
          "icon": "line"
        },
        {
          "type": "website",
          "url": "#",
          "icon": "website"
        }
      ],
      "services": [
        "全球專利商標申請與佈局",
        "智權管理與價值化服務"
      ],
      "hashtags": [
        "#專利商標",
        "#李彥慶",
        "#BNI長輝白金分會"
      ],
      "createdAt": "2025-11-26T01:02:38.842Z",
      "updatedAt": "2025-12-13T16:55:59.175Z",
      "pinHash": "e286648cc9b96588da67f1b8100a650b96850881c79cb777dc88877a3ccfb96f",
      "editCount": 2
    },
    {
      "id": "member-19",
      "name": "楊承樺",
      "photo": "images/members/楊承樺.jpg",
      "industry": "運動營養師",
      "category": "健康美麗",
      "company": "柏飛營養諮詢中心",
      "position": "董事長",
      "title": "董事長 - 柏飛營養諮詢中心",
      "shortIntro": "運動營養 找承樺 讓你增肌減脂 抗老化",
      "fullIntro": "我是楊承樺，專注於運動營養師。\n運動營養 找承樺 讓你增肌減脂 抗老化\n\n【理想引薦對象】\n運動教練、品牌公關公司、健檢單位、檢驗所\n\n【聯絡方式】\n0912-738-335 evolution0105@gmail.com",
      "links": [
        {
          "type": "facebook",
          "url": "#",
          "icon": "facebook"
        },
        {
          "type": "line",
          "url": "#",
          "icon": "line"
        },
        {
          "type": "website",
          "url": "#",
          "icon": "website"
        }
      ],
      "services": [
        "輔導減重/增肌/運動表現提升飲食計劃",
        "演講教育"
      ],
      "hashtags": [
        "#運動營養師",
        "#楊承樺",
        "#BNI長輝白金分會"
      ],
      "createdAt": "2025-11-26T01:02:38.842Z",
      "updatedAt": "2025-12-13T16:55:59.175Z",
      "pinHash": "e286648cc9b96588da67f1b8100a650b96850881c79cb777dc88877a3ccfb96f",
      "editCount": 2
    },
    {
      "id": "member-20",
      "name": "廖涌辰",
      "photo": "images/members/廖涌辰.jpg",
      "industry": "健身教練",
      "category": "健康美麗",
      "company": "好健益運動有限公司",
      "position": "董事長",
      "title": "董事長 - 好健益運動有限公司",
      "shortIntro": "紓壓運動 練肌力 專業教練 好健益",
      "fullIntro": "我是廖涌辰，專注於健身教練。\n紓壓運動 練肌力 專業教練 好健益\n\n【理想引薦對象】\n骨科/復健科醫師、營養師、物理治療師、高爾夫球教練\n\n【聯絡方式】\n0923-253-593 IG:goodideasport",
      "links": [
        {
          "type": "facebook",
          "url": "#",
          "icon": "facebook"
        },
        {
          "type": "line",
          "url": "#",
          "icon": "line"
        },
        {
          "type": "website",
          "url": "#",
          "icon": "website"
        }
      ],
      "services": [
        "客製化私人運動教練課程",
        "居家到府運動教練"
      ],
      "hashtags": [
        "#健身教練",
        "#廖涌辰",
        "#BNI長輝白金分會"
      ],
      "createdAt": "2025-11-26T01:02:38.842Z",
      "updatedAt": "2025-12-13T16:55:59.175Z",
      "pinHash": "e286648cc9b96588da67f1b8100a650b96850881c79cb777dc88877a3ccfb96f",
      "editCount": 2
    },
    {
      "id": "member-21",
      "name": "詹謦鴻",
      "photo": "images/members/詹謦鴻.jpg",
      "industry": "寵物營養",
      "category": "健康美麗",
      "company": "艾特鮮有限公司",
      "position": "董事長",
      "title": "董事長 - 艾特鮮有限公司",
      "shortIntro": "毛孩營養 艾特鮮 專業調理 我推薦",
      "fullIntro": "我是詹謦鴻，專注於寵物營養。\n毛孩營養 艾特鮮 專業調理 我推薦\n\n【理想引薦對象】\n寵物美容、寵物餐廳、寵物行為師\n\n【聯絡方式】\n0988-801651 juliachchan@gmail.com",
      "links": [
        {
          "type": "facebook",
          "url": "#",
          "icon": "facebook"
        },
        {
          "type": "line",
          "url": "#",
          "icon": "line"
        },
        {
          "type": "website",
          "url": "#",
          "icon": "website"
        }
      ],
      "services": [
        "寵物營養諮詢",
        "客製化寵物鮮食"
      ],
      "hashtags": [
        "#寵物營養業",
        "#詹謦鴻",
        "#BNI長輝白金分會"
      ],
      "createdAt": "2025-11-26T01:02:38.843Z",
      "updatedAt": "2025-12-13T16:55:59.175Z",
      "pinHash": "e286648cc9b96588da67f1b8100a650b96850881c79cb777dc88877a3ccfb96f",
      "editCount": 2
    },
    {
      "id": "member-22",
      "name": "洪儀君",
      "photo": "images/members/洪儀君.jpg",
      "industry": "手足指甲保健",
      "category": "健康美麗",
      "company": "健甲專家 H.N.P",
      "position": "董事長",
      "title": "董事長 - 健甲專家 H.N.P",
      "shortIntro": "指甲照護 找儀君 健甲專家 守護您",
      "fullIntro": "我是洪儀君，專注於手足指甲保健。\n指甲照護 找儀君 健甲專家 守護您\n\n【理想引薦對象】\n運動用品店、機能襪業者運動醫學醫師\n\n【聯絡方式】\n0983-401862 Line ID：hnp2016",
      "links": [
        {
          "type": "facebook",
          "url": "#",
          "icon": "facebook"
        },
        {
          "type": "line",
          "url": "#",
          "icon": "line"
        },
        {
          "type": "website",
          "url": "#",
          "icon": "website"
        }
      ],
      "services": [
        "問題甲處理",
        "運動員指甲照護",
        "手足保養 (教育講座 課程服務)"
      ],
      "hashtags": [
        "#手足指甲保健",
        "#洪儀君",
        "#BNI長輝白金分會"
      ],
      "createdAt": "2025-11-26T01:02:38.842Z",
      "updatedAt": "2025-12-13T16:55:59.175Z",
      "pinHash": "e286648cc9b96588da67f1b8100a650b96850881c79cb777dc88877a3ccfb96f",
      "editCount": 2
    },
    {
      "id": "member-23",
      "name": "林庭瑀",
      "photo": "images/members/林庭瑀.jpg",
      "industry": "心靈諮詢",
      "category": "健康美麗",
      "company": "丞妍有限公司",
      "position": "董事長",
      "title": "董事長 - 丞妍有限公司",
      "shortIntro": "遠離負面 與是非 迎向光明 找蘇菲",
      "fullIntro": "我是林庭瑀，專注於心靈諮詢。\n遠離負面 與是非 迎向光明 找蘇菲\n\n【理想引薦對象】\n有情緒與關係困擾 重視員工福利的企業與個人\n\n【聯絡方式】\n0928-486-145 Email：sophibaby@gmail.com",
      "links": [
        {
          "type": "facebook",
          "url": "#",
          "icon": "facebook"
        },
        {
          "type": "line",
          "url": "#",
          "icon": "line"
        },
        {
          "type": "website",
          "url": "#",
          "icon": "website"
        }
      ],
      "services": [
        "個人流年運勢",
        "關係與情緒輔導 企業決策溝通輔導",
        "業務教育訓練"
      ],
      "hashtags": [
        "#心靈諮詢",
        "#林庭瑀",
        "#BNI長輝白金分會"
      ],
      "createdAt": "2025-11-26T01:02:38.842Z",
      "updatedAt": "2025-12-13T16:55:59.175Z",
      "pinHash": "e286648cc9b96588da67f1b8100a650b96850881c79cb777dc88877a3ccfb96f",
      "editCount": 2
    },
    {
      "id": "member-24",
      "name": "鄭雅菁",
      "photo": "images/members/鄭雅菁.jpg",
      "industry": "共享空間",
      "category": "健康美麗",
      "company": "小島好日 LifeArt Studio",
      "position": "董事長",
      "title": "董事長 - 小島好日 LifeArt Studio",
      "shortIntro": "活動空間 找雅菁 與你共創 好業績",
      "fullIntro": "我是鄭雅菁，專注於共享空間。\n活動空間 找雅菁 與你共創 好業績\n\n【理想引薦對象】\n有商攝場地需求的活動 / 廣告公司 有開課、辦講座活動需求的講師/廠商\n\n【聯絡方式】\n0970-862-180 islanday.life@gmail.com",
      "links": [
        {
          "type": "facebook",
          "url": "#",
          "icon": "facebook"
        },
        {
          "type": "line",
          "url": "#",
          "icon": "line"
        },
        {
          "type": "website",
          "url": "#",
          "icon": "website"
        }
      ],
      "services": [
        "場地租借(商攝/講座/活動) 合作開課(烹飪/手作/身心/瑜珈)"
      ],
      "hashtags": [
        "#共享空間",
        "#鄭雅菁",
        "#BNI長輝白金分會"
      ],
      "createdAt": "2025-11-26T01:02:38.843Z",
      "updatedAt": "2025-12-13T16:55:59.175Z",
      "pinHash": "e286648cc9b96588da67f1b8100a650b96850881c79cb777dc88877a3ccfb96f",
      "editCount": 2
    },
    {
      "id": "member-26",
      "name": "李孟一",
      "photo": "images/members/李孟一.jpg",
      "industry": "魔術方塊教學",
      "category": "休閒教育",
      "company": "夢想一號文化教育有限公司",
      "position": "創辦人",
      "title": "創辦人 - 夢想一號文化教育有限公司",
      "shortIntro": "魔術方塊 找孟一 追求夢想 得第一",
      "fullIntro": "我是李孟一，專注於魔術方塊教學。\n魔術方塊 找孟一 追求夢想 得第一\n\n【理想引薦對象】\n想上課的家長、補習班、共學團 課後照顧中學、樂齡學習中心\n\n【聯絡方式】\n0963-237-969 Email：one@dreamcube.tw",
      "links": [
        {
          "type": "website",
          "url": "https://dreamcube.tw",
          "icon": "website"
        },
        {
          "type": "facebook",
          "url": "https://www.facebook.com/DreamOneCubeAcademy",
          "icon": "facebook"
        },
        {
          "type": "youtube",
          "url": "https://www.youtube.com/@DreamOneCubeAcademy",
          "icon": "youtube"
        }
      ],
      "services": [
        "魔術方塊教學",
        "選手培訓"
      ],
      "hashtags": [
        "#魔術方塊教學",
        "#李孟一",
        "#BNI長輝白金分會"
      ],
      "createdAt": "2025-11-26T01:02:38.842Z",
      "updatedAt": "2025-12-13T16:55:59.175Z",
      "pinHash": "e286648cc9b96588da67f1b8100a650b96850881c79cb777dc88877a3ccfb96f",
      "updateCount": 1,
      "editCount": 2
    },
    {
      "id": "member-27",
      "name": "黃昱歆",
      "photo": "images/members/黃昱歆.jpg",
      "industry": "自媒體經營",
      "category": "企業行銷",
      "company": "讓創意飛媒體有限公司",
      "position": "董事長",
      "title": "董事長 - 讓創意飛媒體有限公司",
      "shortIntro": "輕鬆經營 自媒體 創飛趴控 幫助您",
      "fullIntro": "我是黃昱歆，專注於自媒體經營。\n輕鬆經營 自媒體 創飛趴控 幫助您\n\n【理想引薦對象】\n設計師、攝影師、媒體資源\n\n【聯絡方式】\n0988-940-224 Email：jasperysh@gmail.com",
      "links": [
        {
          "type": "facebook",
          "url": "#",
          "icon": "facebook"
        },
        {
          "type": "line",
          "url": "#",
          "icon": "line"
        },
        {
          "type": "website",
          "url": "#",
          "icon": "website"
        }
      ],
      "services": [
        "自媒體經營"
      ],
      "hashtags": [
        "#自媒體經營",
        "#黃昱歆",
        "#BNI長輝白金分會"
      ],
      "createdAt": "2025-11-26T01:02:38.843Z",
      "updatedAt": "2025-12-13T16:55:59.175Z",
      "pinHash": "e286648cc9b96588da67f1b8100a650b96850881c79cb777dc88877a3ccfb96f",
      "editCount": 2
    },
    {
      "id": "member-28",
      "name": "蘇翊婷",
      "photo": "images/members/蘇翊婷.jpg",
      "industry": "茶葉盤商",
      "category": "美食餐飲",
      "company": "茶事漫慢",
      "position": "董事長",
      "title": "董事長 - 茶事漫慢",
      "shortIntro": "想要好茶 找蘇蘇 讓你品質價格 不會 輸",
      "fullIntro": "我是蘇翊婷，專注於茶葉盤商。\n想要好茶 找蘇蘇 讓你品質價格 不會 輸\n\n【理想引薦對象】\n飯店，餐飲，活動行銷公司 公司福委，有喝茶的人\n\n【聯絡方式】\n0955-699-750",
      "links": [
        {
          "type": "facebook",
          "url": "#",
          "icon": "facebook"
        },
        {
          "type": "line",
          "url": "#",
          "icon": "line"
        },
        {
          "type": "website",
          "url": "#",
          "icon": "website"
        }
      ],
      "services": [
        "客製茶葉禮盒",
        "專業高山茶",
        "茶包",
        "冷泡茶"
      ],
      "hashtags": [
        "#茶葉盤商",
        "#蘇翊婷",
        "#BNI長輝白金分會"
      ],
      "createdAt": "2025-11-26T01:02:38.843Z",
      "updatedAt": "2025-12-13T16:55:59.175Z",
      "pinHash": "e286648cc9b96588da67f1b8100a650b96850881c79cb777dc88877a3ccfb96f",
      "editCount": 2
    },
    {
      "id": "member-29",
      "name": "洪智威",
      "photo": "images/members/洪智威.jpg",
      "industry": "空調工程",
      "category": "工程裝修",
      "company": "昇宏空調工程有限公司",
      "position": "董事長",
      "title": "董事長 - 昇宏空調工程有限公司",
      "shortIntro": "居家空調 找智威 專業服務 揪甘心",
      "fullIntro": "我是洪智威，專注於空調工程。\n居家空調 找智威 專業服務 揪甘心\n\n【理想引薦對象】\n散客、建商冷氣代工、全國電子協力廠商\n\n【聯絡方式】\n0956-865-098",
      "links": [
        {
          "type": "facebook",
          "url": "#",
          "icon": "facebook"
        },
        {
          "type": "line",
          "url": "#",
          "icon": "line"
        },
        {
          "type": "website",
          "url": "#",
          "icon": "website"
        }
      ],
      "services": [
        "小冷",
        "居家壁掛+吊隱"
      ],
      "hashtags": [
        "#空調工程",
        "#洪智威",
        "#BNI長輝白金分會"
      ],
      "createdAt": "2025-11-26T01:02:38.842Z",
      "updatedAt": "2025-12-13T16:55:59.175Z",
      "pinHash": "e286648cc9b96588da67f1b8100a650b96850881c79cb777dc88877a3ccfb96f",
      "editCount": 2
    },
    {
      "id": "member-30",
      "name": "郭孝淵",
      "photo": "images/members/郭孝淵.jpg",
      "industry": "包裝設計",
      "category": "工程裝修",
      "company": "提摩設計工作室",
      "position": "董事長",
      "title": "董事長 - 提摩設計工作室",
      "shortIntro": "創意設計 找提摩 企業發展 躍蓬勃",
      "fullIntro": "我是郭孝淵，專注於包裝設計。\n創意設計 找提摩 企業發展 躍蓬勃\n\n【理想引薦對象】\n連鎖餐飲業者以及有禮盒包裝需求，想製作永續包裝的傳產業者\n\n【聯絡方式】\n0913-322-070",
      "links": [
        {
          "type": "facebook",
          "url": "#",
          "icon": "facebook"
        },
        {
          "type": "line",
          "url": "#",
          "icon": "line"
        },
        {
          "type": "website",
          "url": "#",
          "icon": "website"
        }
      ],
      "services": [
        "包裝結構開發",
        "禮盒量產",
        "綠色再生包裝設計"
      ],
      "hashtags": [
        "#工藝設計",
        "#郭孝淵",
        "#BNI長輝白金分會"
      ],
      "createdAt": "2025-11-26T01:02:38.843Z",
      "updatedAt": "2025-12-13T16:55:59.175Z",
      "pinHash": "e286648cc9b96588da67f1b8100a650b96850881c79cb777dc88877a3ccfb96f",
      "editCount": 2
    },
    {
      "id": "member-32",
      "name": "江心怡",
      "photo": "images/members/江心怡.jpg",
      "industry": "LINE應用開發",
      "category": "資訊系統",
      "company": "光隼資訊有限公司",
      "position": "董事長",
      "title": "董事長 - 光隼資訊有限公司",
      "shortIntro": "讓LINE應用 好容易 輕量開發 找心怡",
      "fullIntro": "我是江心怡，專注於LINE應用開發。\n讓LINE應用 好容易 輕量開發 找心怡\n\n【理想引薦對象】\n醫美診所或美業相關工作者\n\n【聯絡方式】\nLINE ID: Lingchiang0831/0922930621",
      "links": [
        {
          "type": "facebook",
          "url": "#",
          "icon": "facebook"
        },
        {
          "type": "line",
          "url": "#",
          "icon": "line"
        },
        {
          "type": "website",
          "url": "#",
          "icon": "website"
        }
      ],
      "services": [
        "LINE@QA圖文chatbot",
        "會員管理",
        "定期連絡",
        "電子名片",
        "報名預約功能",
        "購物商城",
        "分潤機制"
      ],
      "hashtags": [
        "#LINE 應用開發",
        "#江心怡",
        "#BNI長輝白金分會"
      ],
      "createdAt": "2025-11-26T01:02:38.842Z",
      "updatedAt": "2025-12-13T16:55:59.175Z",
      "pinHash": "e286648cc9b96588da67f1b8100a650b96850881c79cb777dc88877a3ccfb96f",
      "editCount": 2
    },
    {
      "id": "member-33",
      "name": "施秉辰",
      "photoPosition": "top",
      "photo": "images/members/施秉辰.jpg",
      "industry": "資訊弱電系統整合",
      "category": "資訊系統",
      "company": "驊程科技股份有限公司",
      "position": "董事長",
      "title": "董事長 - 驊程科技股份有限公司",
      "shortIntro": "資訊弱電 大小事 交給秉辰 全搞定",
      "fullIntro": "我是施秉辰，專注於資訊弱電系統整合。\n資訊弱電 大小事 交給秉辰 全搞定\n\n【理想引薦對象】\n室內設計師、工程統包、各種工班\n\n【聯絡方式】\n0931-049-858 Line：addams.shih",
      "links": [
        {
          "type": "facebook",
          "url": "#",
          "icon": "facebook"
        },
        {
          "type": "line",
          "url": "#",
          "icon": "line"
        },
        {
          "type": "website",
          "url": "#",
          "icon": "website"
        }
      ],
      "services": [
        "資訊設備軟硬體整合服務",
        "弱電設備規劃建置"
      ],
      "hashtags": [
        "#資訊弱電系統整合",
        "#施秉辰",
        "#BNI長輝白金分會"
      ],
      "createdAt": "2025-11-26T01:02:38.842Z",
      "updatedAt": "2025-12-13T16:55:59.175Z",
      "pinHash": "e286648cc9b96588da67f1b8100a650b96850881c79cb777dc88877a3ccfb96f",
      "editCount": 2
    },
    {
      "id": "member-34",
      "name": "李秉誠",
      "photo": "images/members/李秉誠.jpg",
      "industry": "包租代管",
      "category": "企業顧問",
      "company": "楓烽管理顧問有限公司",
      "position": "董事長",
      "title": "董事長 - 楓烽管理顧問有限公司",
      "shortIntro": "包租代管 找亨利 讓你省時 又省力",
      "fullIntro": "我是李秉誠，專注於包租代管。\n包租代管 找亨利 讓你省時 又省力\n\n【理想引薦對象】\n房屋仲介、包租公、包租婆\n\n【聯絡方式】\n0901395543 Line：Ibc12345",
      "links": [
        {
          "type": "facebook",
          "url": "#",
          "icon": "facebook"
        },
        {
          "type": "line",
          "url": "#",
          "icon": "line"
        },
        {
          "type": "website",
          "url": "#",
          "icon": "website"
        }
      ],
      "services": [
        "包租代管服務",
        "專業房屋管理",
        "房屋修繕 媒合屋主租客",
        "催收租金",
        "老屋改建增加收益"
      ],
      "hashtags": [
        "#包租代管",
        "#李秉誠",
        "#BNI長輝白金分會"
      ],
      "createdAt": "2025-11-26T01:02:38.842Z",
      "updatedAt": "2025-12-13T16:55:59.175Z",
      "pinHash": "e286648cc9b96588da67f1b8100a650b96850881c79cb777dc88877a3ccfb96f",
      "editCount": 2
    },
    {
      "id": "member-36",
      "name": "徐采璇",
      "photo": "images/members/徐采璇.jpg",
      "industry": "原型食物料理師",
      "category": "美食餐飲",
      "company": "錢自來綜合餐飲坊",
      "position": "董事長",
      "title": "董事長 - 錢自來綜合餐飲坊",
      "shortIntro": "身體秘密 玄又玄 飲食協助 找采璇",
      "fullIntro": "我是徐采璇，專注於原型食物料理師。\n身體秘密 玄又玄 飲食協助 找采璇\n\n【理想引薦對象】\n火鍋店 咖啡廳 產婦 注重健康長輩\n\n【聯絡方式】\n0977152710",
      "links": [
        {
          "type": "facebook",
          "url": "#",
          "icon": "facebook"
        },
        {
          "type": "line",
          "url": "#",
          "icon": "line"
        },
        {
          "type": "website",
          "url": "#",
          "icon": "website"
        }
      ],
      "services": [
        "三無原型食物餐廳",
        "三無即食包",
        "無糖",
        "無奶",
        "無麩質食物製作",
        "身心靈需要好好被照顧的好食物"
      ],
      "hashtags": [
        "#原型食物料理師",
        "#徐采璇",
        "#BNI長輝白金分會"
      ],
      "createdAt": "2025-11-26T01:02:38.842Z",
      "updatedAt": "2025-12-13T16:55:59.175Z",
      "pinHash": "e286648cc9b96588da67f1b8100a650b96850881c79cb777dc88877a3ccfb96f",
      "editCount": 2
    },
    {
      "id": "member-37",
      "name": "王祈",
      "photo": "images/members/王祈.jpg",
      "industry": "ai學習整合",
      "category": "休閒教育",
      "company": "祈育教育實業坊",
      "position": "董事長",
      "title": "董事長 - 祈育教育實業坊",
      "shortIntro": "A I 學習 找王祈 科技賦能 正黃旗",
      "fullIntro": "我是王祈，專注於AI學習整合。\nA I 學習 找王祈 科技賦能 正黃旗\n\n【理想引薦對象】\n尋求職涯成長的專業人士、各級學生 (國中至大學)、企業AI內訓\n\n【聯絡方式】\n0956522350",
      "links": [
        {
          "type": "instagram",
          "url": "https://www.instagram.com/samuel_wang0731",
          "icon": "instagram"
        },
        {
          "type": "website",
          "url": "mailto:samuel900731@gmail.com",
          "icon": "website"
        }
      ],
      "services": [
        "教育賦能",
        "AI應用學習"
      ],
      "hashtags": [
        "#AI學習整合",
        "#王祈",
        "#BNI長輝白金分會"
      ],
      "createdAt": "2025-11-26T01:02:38.843Z",
      "updatedAt": "2025-12-13T16:55:59.175Z",
      "pinHash": "e286648cc9b96588da67f1b8100a650b96850881c79cb777dc88877a3ccfb96f",
      "editCount": 2
    },
    {
      "id": "member-38",
      "name": "賴永相",
      "photo": "images/members/賴永相.jpg",
      "industry": "堅果烘焙業",
      "category": "美食餐飲",
      "company": "大象山食品有限公司",
      "position": "董事長",
      "title": "董事長 - 大象山食品有限公司",
      "shortIntro": "身體健康 吃堅果 烘培堅果 大象山",
      "fullIntro": "我是賴永相，專注於堅果烘焙業。\n身體健康 吃堅果 烘培堅果 大象山\n\n【理想引薦對象】\n團購直播主 高爾夫球隊\n\n【聯絡方式】\n0935553726 elephant552726@yahoo.com.tw",
      "links": [
        {
          "type": "facebook",
          "url": "#",
          "icon": "facebook"
        },
        {
          "type": "line",
          "url": "#",
          "icon": "line"
        },
        {
          "type": "website",
          "url": "#",
          "icon": "website"
        }
      ],
      "services": [
        "自營堅果品牌-大象山 堅果禮盒 OEM堅果"
      ],
      "hashtags": [
        "#堅果烘焙業",
        "#賴永相",
        "#BNI長輝白金分會"
      ],
      "createdAt": "2025-11-26T01:02:38.843Z",
      "updatedAt": "2025-12-13T16:55:59.175Z",
      "pinHash": "e286648cc9b96588da67f1b8100a650b96850881c79cb777dc88877a3ccfb96f",
      "editCount": 2
    },
    {
      "id": "member-39",
      "name": "蘇子超",
      "photo": "images/members/蘇子超.jpg",
      "industry": "電子商品設計",
      "category": "企業顧問",
      "company": "廣謙科技有限公司",
      "position": "董事長",
      "title": "董事長 - 廣謙科技有限公司",
      "shortIntro": "電子設計 找子超 熱賣狂銷 數紙鈔",
      "fullIntro": "我是蘇子超，專注於電子商品設計。\n電子設計 找子超 熱賣狂銷 數紙鈔\n\n【理想引薦對象】\n工業設計、專利師、新創投資\n\n【聯絡方式】\n0926-190980",
      "links": [
        {
          "type": "facebook",
          "url": "#",
          "icon": "facebook"
        },
        {
          "type": "line",
          "url": "#",
          "icon": "line"
        },
        {
          "type": "website",
          "url": "#",
          "icon": "website"
        }
      ],
      "services": [
        "電子商品設計",
        "電子商品生產及製作"
      ],
      "hashtags": [
        "#電子商品設計",
        "#蘇子超",
        "#BNI長輝白金分會"
      ],
      "createdAt": "2025-11-26T01:02:38.843Z",
      "updatedAt": "2025-12-13T16:55:59.175Z",
      "pinHash": "e286648cc9b96588da67f1b8100a650b96850881c79cb777dc88877a3ccfb96f",
      "editCount": 2
    },
    {
      "id": "member-40",
      "name": "李維恩",
      "photo": "images/members/李維恩.jpg",
      "industry": "網站創新開發",
      "category": "資訊系統",
      "company": "艾思特創新設計有限公司",
      "position": "董事長",
      "title": "董事長 - 艾思特創新設計有限公司",
      "shortIntro": "網站APP 找維恩 數位創新 賺大錢",
      "fullIntro": "我是李維恩，專注於網站創新開發。\n網站APP 找維恩 數位創新 賺大錢\n\n【理想引薦對象】\n企業顧問、資訊顧問、品牌設計、網路行銷\n\n【聯絡方式】\n0933-721-702",
      "links": [
        {
          "type": "facebook",
          "url": "#",
          "icon": "facebook"
        },
        {
          "type": "line",
          "url": "#",
          "icon": "line"
        },
        {
          "type": "website",
          "url": "#",
          "icon": "website"
        }
      ],
      "services": [
        "專注於：網站 / APP / 系統 / AI"
      ],
      "hashtags": [
        "#APP 設計開發",
        "#李維恩",
        "#BNI長輝白金分會"
      ],
      "createdAt": "2025-11-26T01:02:38.842Z",
      "updatedAt": "2025-12-13T16:55:59.175Z",
      "pinHash": "e286648cc9b96588da67f1b8100a650b96850881c79cb777dc88877a3ccfb96f",
      "editCount": 2
    },
    {
      "id": "member-41",
      "name": "吳貞妮",
      "photo": "images/members/吳貞妮.jpg",
      "industry": "插畫設計",
      "category": "企業行銷",
      "company": "拉蒂設計LuxurWind_個人工作室",
      "position": "董事長",
      "title": "董事長 - 拉蒂設計LuxurWind_個人工作室",
      "shortIntro": "蒂造形象新花浪 插畫設計找貞妮",
      "fullIntro": "我是吳貞妮，專注於插畫設計。\n蒂造形象新花浪 插畫設計找貞妮\n\n【理想引薦對象】\n品牌行銷、社群網紅、遊戲公司\n\n【聯絡方式】\n0909-016-990",
      "links": [
        {
          "type": "facebook",
          "url": "#",
          "icon": "facebook"
        },
        {
          "type": "line",
          "url": "#",
          "icon": "line"
        },
        {
          "type": "website",
          "url": "#",
          "icon": "website"
        }
      ],
      "services": [
        "客製化貼圖",
        "插畫吉祥物"
      ],
      "hashtags": [
        "#貼圖設計",
        "#吳貞妮",
        "#BNI長輝白金分會"
      ],
      "createdAt": "2025-11-26T01:02:38.842Z",
      "updatedAt": "2025-12-13T16:55:59.175Z",
      "pinHash": "e286648cc9b96588da67f1b8100a650b96850881c79cb777dc88877a3ccfb96f",
      "editCount": 2
    },
    {
      "id": "member-43",
      "name": "吳宇峰",
      "photo": "images/members/吳宇峰.jpg",
      "industry": "泥作工程",
      "category": "工程裝修",
      "company": "峰翔工程行",
      "position": "董事長",
      "title": "董事長 - 峰翔工程行",
      "shortIntro": "泥作工程 找宇峰 品質工法 樣樣通",
      "fullIntro": "我是吳宇峰，專注於泥作工程。\n泥作工程 找宇峰 品質工法 樣樣通\n\n【理想引薦對象】\n統包工程、室內設計師、營造廠\n\n【聯絡方式】\n0935-111-222",
      "links": [
        {
          "type": "facebook",
          "url": "#",
          "icon": "facebook"
        },
        {
          "type": "line",
          "url": "#",
          "icon": "line"
        },
        {
          "type": "website",
          "url": "#",
          "icon": "website"
        }
      ],
      "services": [
        "泥作工程承包",
        "防水工程",
        "磁磚鋪設"
      ],
      "hashtags": [
        "#泥作工程",
        "#吳宇峰",
        "#BNI長輝白金分會"
      ],
      "createdAt": "2025-11-26T01:02:38.842Z",
      "updatedAt": "2025-12-13T16:42:16.100Z",
      "pinHash": "e286648cc9b96588da67f1b8100a650b96850881c79cb777dc88877a3ccfb96f",
      "editCount": 1
    },
    {
      "id": "member-44",
      "name": "劉懿德",
      "photo": "images/members/劉懿德.jpg",
      "industry": "策展規劃設計",
      "category": "工程裝修",
      "company": "樂橙創作設計",
      "position": "董事長",
      "title": "董事長 - 樂橙創作設計",
      "shortIntro": "策展規劃 大小事 交給阿德 無難事",
      "fullIntro": "我是劉懿德，專注於策展規劃設計。\n策展規劃 大小事 交給阿德 無難事\n\n【理想引薦對象】\n公司工廠展示空間/ESG展示\n\n【聯絡方式】\n0952-983-157 Email：claire@allrange.tw",
      "links": [
        {
          "type": "facebook",
          "url": "#",
          "icon": "facebook"
        },
        {
          "type": "line",
          "url": "#",
          "icon": "line"
        },
        {
          "type": "website",
          "url": "#",
          "icon": "website"
        }
      ],
      "services": [
        "公司或傳產工廠轉型展示規劃",
        "短中長期活動展場設計 從設計提案3D到發包施工",
        "一條龍的服務。"
      ],
      "hashtags": [
        "#策展規劃設計",
        "#劉懿德",
        "#BNI長輝白金分會"
      ],
      "createdAt": "2025-11-26T01:02:38.842Z",
      "updatedAt": "2025-12-13T16:55:59.175Z",
      "pinHash": "e286648cc9b96588da67f1b8100a650b96850881c79cb777dc88877a3ccfb96f",
      "editCount": 2
    },
    {
      "id": "member-45",
      "name": "游凱地",
      "photo": "images/members/游凱地.jpg",
      "industry": "抗病毒地板",
      "category": "工程裝修",
      "company": "鉅成工業股份有限公司",
      "position": "董事長",
      "title": "董事長 - 鉅成工業股份有限公司",
      "shortIntro": "地板需求 找凱地 商空住家 皆適宜",
      "fullIntro": "我是游凱地，專注於抗病毒地板。\n地板需求 找凱地 商空住家 皆適宜\n\n【理想引薦對象】\n建商、工程承包商、設計師、 電商平台\n\n【聯絡方式】\n0988-568-819 Email：ktyu@kingtile.com.tw",
      "links": [
        {
          "type": "facebook",
          "url": "#",
          "icon": "facebook"
        },
        {
          "type": "line",
          "url": "#",
          "icon": "line"
        },
        {
          "type": "website",
          "url": "#",
          "icon": "website"
        }
      ],
      "services": [
        "PVC地板製造",
        "抗病毒SPC地板",
        "免膠兒童地板 抗病毒防疫建材",
        "塗布技術"
      ],
      "hashtags": [
        "#抗病毒地板",
        "#游凱地",
        "#BNI長輝白金分會"
      ],
      "createdAt": "2025-11-26T01:02:38.842Z",
      "updatedAt": "2025-12-13T16:55:59.175Z",
      "pinHash": "e286648cc9b96588da67f1b8100a650b96850881c79cb777dc88877a3ccfb96f",
      "editCount": 2
    },
    {
      "id": "member-46",
      "name": "邱翰城",
      "photo": "images/members/邱翰城.jpg",
      "industry": "創意策劃",
      "category": "企業行銷",
      "company": "分子藝術有限公司",
      "position": "董事長",
      "title": "董事長 - 分子藝術有限公司",
      "shortIntro": "創意策劃 找多多 出神入化 Magical",
      "fullIntro": "我是邱翰城，專注於創意策劃。\n創意策劃 找多多 出神入化 Magical\n\n【理想引薦對象】\n策展人、品牌公關、 餐飲旅宿品牌\n\n【聯絡方式】\n0978-110-365 Email：kk955172@gmail.com Line：kk955172",
      "links": [
        {
          "type": "facebook",
          "url": "#",
          "icon": "facebook"
        },
        {
          "type": "line",
          "url": "#",
          "icon": "line"
        },
        {
          "type": "website",
          "url": "#",
          "icon": "website"
        }
      ],
      "services": [
        "品牌故事企劃",
        "互動故事體驗",
        "跨領域藝術整合企劃"
      ],
      "hashtags": [
        "#創意策劃",
        "#邱翰城",
        "#BNI長輝白金分會"
      ],
      "createdAt": "2025-11-26T01:02:38.843Z",
      "updatedAt": "2025-12-13T16:55:59.175Z",
      "pinHash": "e286648cc9b96588da67f1b8100a650b96850881c79cb777dc88877a3ccfb96f",
      "editCount": 2
    },
    {
      "id": "member-48",
      "name": "楊明翰",
      "photo": "images/members/楊明翰.jpg",
      "industry": "機電設計",
      "category": "健康美麗",
      "company": "欣楠科技股份有限公司",
      "position": "董事長",
      "title": "董事長 - 欣楠科技股份有限公司",
      "shortIntro": "機電設計 找明翰 智能創新 沒煩惱",
      "fullIntro": "我是楊明翰，專注於機電設計。\n機電設計 找明翰 智能創新 沒煩惱\n\n【理想引薦對象】\n統包工程、室內裝修、室內設計師\n\n【聯絡方式】\n0978059263 mail：sunshineminghan@gmail.com",
      "links": [
        {
          "type": "facebook",
          "url": "#",
          "icon": "facebook"
        },
        {
          "type": "line",
          "url": "#",
          "icon": "line"
        },
        {
          "type": "website",
          "url": "#",
          "icon": "website"
        }
      ],
      "services": [
        "機電規劃",
        "設計",
        "施工",
        "監工",
        "完工",
        "測試",
        "後續使用中的開機操作",
        "維護保養。"
      ],
      "hashtags": [
        "#產物保險規劃",
        "#楊明翰",
        "#BNI長輝白金分會"
      ],
      "createdAt": "2025-11-26T01:02:38.842Z",
      "updatedAt": "2025-12-13T16:55:59.176Z",
      "pinHash": "e286648cc9b96588da67f1b8100a650b96850881c79cb777dc88877a3ccfb96f",
      "editCount": 3
    },
    {
      "id": "member-49",
      "name": "顧心芝",
      "photo": "images/members/顧心芝.jpg",
      "industry": "餐飲行銷整合",
      "category": "企業行銷",
      "company": "禾望品牌股份有限公司",
      "position": "董事長",
      "title": "董事長 - 禾望品牌股份有限公司",
      "shortIntro": "餐飲創業 找禾望 一起豐收 沒煩惱",
      "fullIntro": "我是顧心芝，專注於餐飲行銷整合。\n餐飲創業 找禾望 一起豐收 沒煩惱\n\n【理想引薦對象】\n想要在餐飲市場創業，或者已經創業需要重新規劃\n\n【聯絡方式】\n0921-856-976 Email：design@havest4hope.com",
      "links": [
        {
          "type": "facebook",
          "url": "#",
          "icon": "facebook"
        },
        {
          "type": "line",
          "url": "#",
          "icon": "line"
        },
        {
          "type": "website",
          "url": "#",
          "icon": "website"
        }
      ],
      "services": [
        "服務項目：餐飲行銷整合規劃 開店大小事",
        "都是我們的事 餐飲品牌量身定做",
        "店面規劃",
        "餐飲研發",
        "人事訓練",
        "從零開始",
        "搞定你的餐飲創業大小事"
      ],
      "hashtags": [
        "#餐飲行銷整合",
        "#顧心芝",
        "#BNI長輝白金分會"
      ],
      "createdAt": "2025-11-26T01:02:38.843Z",
      "updatedAt": "2025-12-13T16:55:59.175Z",
      "pinHash": "e286648cc9b96588da67f1b8100a650b96850881c79cb777dc88877a3ccfb96f",
      "editCount": 2
    },
    {
      "id": "member-50",
      "name": "陳亭儒",
      "photo": "images/members/陳亭儒.jpg",
      "industry": "銀行融資顧問",
      "category": "企業顧問",
      "company": "元創財富管理顧問有限公司",
      "position": "董事長",
      "title": "董事長 - 元創財富管理顧問有限公司",
      "shortIntro": "貸款需求 找亭儒 簡單快速 好幸福",
      "fullIntro": "我是陳亭儒，專注於銀行融資顧問。\n貸款需求 找亭儒 簡單快速 好幸福\n\n【理想引薦對象】\n保險業務員、律師、會計師 理財顧問\n\n【聯絡方式】\n0988-923-104",
      "links": [
        {
          "type": "facebook",
          "url": "#",
          "icon": "facebook"
        },
        {
          "type": "line",
          "url": "#",
          "icon": "line"
        },
        {
          "type": "website",
          "url": "#",
          "icon": "website"
        }
      ],
      "services": [
        "銀行融資貸款 協助新創公司融資擴大營業",
        "辦理預備金",
        "申請創業青年貸款需求",
        "申辦房貸20年寬限期貸款"
      ],
      "hashtags": [
        "#銀行融資顧問",
        "#陳亭儒",
        "#BNI長輝白金分會"
      ],
      "createdAt": "2025-11-26T01:02:38.843Z",
      "updatedAt": "2025-12-13T16:55:59.175Z",
      "pinHash": "e286648cc9b96588da67f1b8100a650b96850881c79cb777dc88877a3ccfb96f",
      "editCount": 2
    },
    {
      "id": "member-51",
      "name": "陳夗媃",
      "photo": "images/members/陳夗媃.jpg",
      "industry": "澎湖特色餐飲",
      "category": "美食餐飲",
      "company": "半日閑企業行",
      "position": "董事長",
      "title": "董事長 - 半日閑企業行",
      "shortIntro": "澎湖旅遊 享新鮮 美食甜點 半日閑",
      "fullIntro": "我是陳夗媃，專注於澎湖特色餐飲。\n澎湖旅遊 享新鮮 美食甜點 半日閑\n\n【理想引薦對象】\n旅行社、公司活動部\n\n【聯絡方式】\n06-921-1007",
      "links": [
        {
          "type": "facebook",
          "url": "#",
          "icon": "facebook"
        },
        {
          "type": "line",
          "url": "#",
          "icon": "line"
        },
        {
          "type": "website",
          "url": "#",
          "icon": "website"
        }
      ],
      "services": [
        "澎湖美食甜點",
        "團體包場 咖啡",
        "甜點",
        "美食宅配",
        "澎湖特產宅配"
      ],
      "hashtags": [
        "#澎湖特色餐飲",
        "#陳夗媃",
        "#BNI長輝白金分會"
      ],
      "createdAt": "2025-11-26T01:02:38.843Z",
      "updatedAt": "2025-12-13T16:55:59.175Z",
      "pinHash": "e286648cc9b96588da67f1b8100a650b96850881c79cb777dc88877a3ccfb96f",
      "editCount": 2
    },
    {
      "id": "member-53",
      "name": "王年煜",
      "photo": "images/members/王年煜.jpg",
      "industry": "AI程式交易",
      "category": "投資理財",
      "company": "創達智能技術股份有限公司",
      "position": "董事長",
      "title": "董事長 - 創達智能技術股份有限公司",
      "shortIntro": "程式交易 很容易 穩定獲利 找年煜",
      "fullIntro": "我是王年煜，專注於AI程式交易。\n程式交易 很容易 穩定獲利 找年煜\n\n【理想引薦對象】\n有理財需求的公司與個人、想替自己客戶尋找穩定收益的理財產品、對開發人工智慧應用有興趣的公司或個人\n\n【聯絡方式】\n0938-767-768 Mail：wang.ian@investrontech.com",
      "links": [
        {
          "type": "facebook",
          "url": "#",
          "icon": "facebook"
        },
        {
          "type": "line",
          "url": "#",
          "icon": "line"
        },
        {
          "type": "website",
          "url": "#",
          "icon": "website"
        }
      ],
      "services": [
        "人工智慧 & 外匯交易"
      ],
      "hashtags": [
        "#AI程式交易",
        "#王年煜",
        "#BNI長輝白金分會"
      ],
      "createdAt": "2025-11-26T01:02:38.843Z",
      "updatedAt": "2025-12-13T16:55:59.175Z",
      "pinHash": "e286648cc9b96588da67f1b8100a650b96850881c79cb777dc88877a3ccfb96f",
      "editCount": 2
    },
    {
      "id": "member-54",
      "name": "王銓",
      "photo": "images/members/王銓.jpg",
      "industry": "ai商務顧問",
      "category": "資訊系統",
      "company": "三人科技顧問 (三人數位科技有限公司 )",
      "position": "創辦人",
      "title": "創辦人 - 三人科技顧問 (三人數位科技有限公司 )",
      "shortIntro": "AI服務 組合拳 幫你創新 找王銓",
      "fullIntro": "我是王銓，專注於AI商務顧問。\nAI服務 組合拳 幫你創新 找王銓\n\n【理想引薦對象】\n行政繁瑣的中小企業、想解放工作時間的工作者\n\n【聯絡方式】\n0911-309-998 E-Mail：wang.business.a@gmail.com",
      "links": [
        {
          "type": "facebook",
          "url": "#測試連結",
          "icon": "facebook"
        },
        {
          "type": "line",
          "url": "#",
          "icon": "line"
        },
        {
          "type": "website",
          "url": "#",
          "icon": "website"
        }
      ],
      "services": [
        "客製AI自動化系統",
        "AI工具導入"
      ],
      "hashtags": [
        "#AI 程式教育",
        "#王銓",
        "#BNI長輝白金分會"
      ],
      "createdAt": "2025-11-26T01:02:38.843Z",
      "updatedAt": "2025-12-13T16:55:59.175Z",
      "pinHash": "e286648cc9b96588da67f1b8100a650b96850881c79cb777dc88877a3ccfb96f",
      "updateCount": 1,
      "editCount": 2
    },

    {
      "id": "member-56",
      "name": "李慰祖",
      "photo": "images/members/李慰祖.jpg",
      "industry": "團體服業",
      "category": "企業行銷",
      "company": "悅爾企業有限公司",
      "position": "董事長",
      "title": "董事長 - 悅爾企業有限公司",
      "shortIntro": "團體服裝 找姐夫（Jeffrey） 品質形象 不馬虎",
      "fullIntro": "我是李慰祖，專注於團體服業。\n團體服裝 找姐夫（Jeffrey） 品質形象 不馬虎\n\n【理想引薦對象】\n公司行號、公司團體、公關行銷、標案合作\n\n【聯絡方式】\n0903-995105 Line ID: jwl8477",
      "links": [
        {
          "type": "facebook",
          "url": "#",
          "icon": "facebook"
        },
        {
          "type": "line",
          "url": "#",
          "icon": "line"
        },
        {
          "type": "website",
          "url": "#",
          "icon": "website"
        }
      ],
      "services": [
        "針對公營及民營團體與學校 提供各種款式團體服裝設計",
        "製作"
      ],
      "hashtags": [
        "#團體服業",
        "#李慰祖",
        "#BNI長輝白金分會"
      ],
      "createdAt": "2025-11-26T01:02:38.842Z",
      "updatedAt": "2025-12-13T16:55:59.175Z",
      "pinHash": "e286648cc9b96588da67f1b8100a650b96850881c79cb777dc88877a3ccfb96f",
      "editCount": 2
    },
    {
      "id": "member-57",
      "name": "吳睿霖",
      "photo": "images/members/吳睿霖.jpg",
      "industry": "統包工程",
      "category": "工程裝修",
      "company": "元允室內裝修工程有限公司",
      "position": "董事長",
      "title": "董事長 - 元允室內裝修工程有限公司",
      "shortIntro": "工程統包 找睿霖 進度品管 最放心",
      "fullIntro": "我是吳睿霖，專注於統包工程。\n工程統包 找睿霖 進度品管 最放心\n\n【理想引薦對象】\n營造廠、建設公司、設計公司\n\n【聯絡方式】\n0938-541-940",
      "links": [
        {
          "type": "facebook",
          "url": "#",
          "icon": "facebook"
        },
        {
          "type": "line",
          "url": "#",
          "icon": "line"
        },
        {
          "type": "website",
          "url": "#",
          "icon": "website"
        }
      ],
      "services": [
        "建案",
        "商業",
        "住宅工程統包及木作工程"
      ],
      "hashtags": [
        "#統包工程",
        "#吳睿霖",
        "#BNI長輝白金分會"
      ],
      "createdAt": "2025-11-26T01:02:38.842Z",
      "updatedAt": "2025-12-13T16:55:59.175Z",
      "pinHash": "e286648cc9b96588da67f1b8100a650b96850881c79cb777dc88877a3ccfb96f",
      "editCount": 2
    },
    {
      "id": "member-58",
      "name": "許雅婷",
      "photo": "images/members/許雅婷.jpg",
      "industry": "人力媒合平台",
      "category": "企業顧問",
      "company": "沃祈數位科技股份有限公司",
      "position": "行銷副總",
      "title": "行銷副總 - 沃祈數位科技股份有限公司",
      "shortIntro": "worky信的過 更好用 一鍵派工 超輕鬆",
      "fullIntro": "我是許雅婷，專注於人力媒合平台。\nworky信的過 更好用 一鍵派工 超輕鬆\n\n【理想引薦對象】\n商家老闆、有人力需求的店家和企業、連鎖企業、有短期工作需求者\n\n【聯絡方式】\n0920808788 mail:angela.hsu@gamehours.com",
      "links": [
        {
          "type": "website",
          "url": "#",
          "icon": "website"
        }
      ],
      "services": [
        "快速協助商家解決缺工問題並 節省時間與人力成本。"
      ],
      "hashtags": [
        "#人力媒合",
        "#Worky",
        "#許雅婷",
        "#BNI長輝白金分會"
      ],
      "createdAt": "2025-12-13T09:00:00.000Z",
      "updatedAt": "2025-12-13T16:55:59.176Z",
      "pinHash": "e286648cc9b96588da67f1b8100a650b96850881c79cb777dc88877a3ccfb96f",
      "editCount": 2
    },
    {
      "id": "member-1765644136096-488",
      "name": "彭顯智",
      "photo": "images/members/彭顯智.jpg",
      "industry": "居家鍍膜",
      "company": "圭葆有限公司",
      "position": "負責人",
      "title": "負責人 - 圭葆有限公司",
      "shortIntro": "居家鍍膜 找顯智 潔淨生活 更舒適",
      "fullIntro": "我是彭顯智，專注於居家鍍膜。\n居家鍍膜 找顯智 潔淨生活 更舒適\n\n【理想引薦對象】\n設計師、裝修公司、清潔業者、物業管理、民宿與商用空間業主\n\n【聯絡方式】\n0978-178-488 mail：genius.hcpeng@gmail.com",
      "links": [
        {
          "type": "website",
          "url": "#",
          "icon": "website"
        }
      ],
      "services": [
        "居家鍍膜產品",
        "抗菌防護層",
        "廚衛耐污鍍膜",
        "玻璃防水鍍膜",
        "家俱表面保護",
        "清潔效能提升方案"
      ],
      "hashtags": [
        "#居家鍍膜",
        "#彭顯智"
      ],
      "createdAt": "2025-12-13T16:42:16.096Z",
      "updatedAt": "2025-12-13T16:55:59.178Z",
      "category": "",
      "editCount": 2
    },
    {
      "id": "member-1765644959176-2433",
      "name": "劉弼凱",
      "photo": "images/members/劉弼凱.jpg",
      "industry": "水電工程",
      "company": "雷水有限公司",
      "position": "負責人",
      "title": "水電工程 專家",
      "shortIntro": "案場工程 找水電 雷水讓你 尚放心",
      "fullIntro": "我是劉弼凱，專注於水電工程。\n案場工程 找水電 雷水讓你 尚放心\n\n【理想引薦對象】\n設計師/建築師/統包公司\n\n【聯絡方式】\n0929-853-311 mail：l.shuei1113@gmail.com",
      "links": [
        {
          "type": "website",
          "url": "#",
          "icon": "website"
        }
      ],
      "services": [
        "建築物專用水電工程",
        "配合設計師/建築師/ 統包公司",
        "為您特製合法合規的水+電。"
      ],
      "hashtags": [
        "#水電工程",
        "#劉弼凱"
      ],
      "createdAt": "2025-12-13T16:55:59.176Z",
      "updatedAt": "2025-12-13T16:55:59.176Z",
      "category": "",
      "editCount": 1
    },
    {
      "id": "member-1765644959177-5428",
      "name": "潘芷盈",
      "photo": "images/members/潘芷盈.jpg",
      "industry": "SEO 內容行銷",
      "company": "最準行銷服務有限公司",
      "position": "負責人",
      "title": "SEO 內容行銷 專家",
      "shortIntro": "精準流量 全代操 客戶上門 免煩惱",
      "fullIntro": "我是潘芷盈，專注於SEO 內容行銷。\n精準流量 全代操 客戶上門 免煩惱\n\n【理想引薦對象】\n行銷公司、品牌顧問、電商系統\n\n【聯絡方式】\n0975042077、 jadepang418@gmail.com",
      "links": [
        {
          "type": "website",
          "url": "#",
          "icon": "website"
        }
      ],
      "services": [
        "免費架網站",
        "免費寫文章",
        "有效才付費"
      ],
      "hashtags": [
        "#SEO 內容行銷",
        "#潘芷盈"
      ],
      "createdAt": "2025-12-13T16:55:59.177Z",
      "updatedAt": "2025-12-13T16:55:59.177Z",
      "category": "",
      "editCount": 1
    },
    {
      "id": "member-1765644959177-6105",
      "name": "湯益承",
      "photo": "images/members/湯益承.jpg",
      "industry": "永續可分解包裝",
      "company": "謙益科技股份有限公司",
      "position": "負責人",
      "title": "永續可分解包裝 專家",
      "shortIntro": "分解包裝 找益承 袋袋永續 有保證",
      "fullIntro": "我是湯益承，專注於永續可分解包裝。\n分解包裝 找益承 袋袋永續 有保證\n\n【理想引薦對象】\n飯店旅宿業，團購主，家樂福，全聯採購\n\n【聯絡方式】\n0930857662 mail:pm1modesty@gmail.com",
      "links": [
        {
          "type": "website",
          "url": "#",
          "icon": "website"
        }
      ],
      "services": [
        "夾鏈袋",
        "垃圾袋",
        "蔬果袋",
        "麵包袋",
        "拾狗便袋 等公版與客製化包裝袋服務"
      ],
      "hashtags": [
        "#永續可分解包裝",
        "#湯益承"
      ],
      "createdAt": "2025-12-13T16:55:59.177Z",
      "updatedAt": "2025-12-13T16:55:59.177Z",
      "category": "",
      "editCount": 1
    },
    {
      "id": "member-1765644959178-278",
      "name": "呂學承",
      "photo": "images/members/呂學承.jpg",
      "industry": "汽車租賃",
      "company": "富豪聯合租賃股份有限公司",
      "position": "負責人",
      "title": "汽車租賃 專家",
      "shortIntro": "汽車租賃 找富豪 事業馬上 變富豪",
      "fullIntro": "我是呂學承，專注於汽車租賃。\n汽車租賃 找富豪 事業馬上 變富豪\n\n【理想引薦對象】\n半導體與科技廠區/建設公司/代銷不動產/ 宗教協會工會\n\n【聯絡方式】\n0928-834-212 mail：alexlu@am-asap.com",
      "links": [
        {
          "type": "website",
          "url": "#",
          "icon": "website"
        }
      ],
      "services": [
        "企業租車",
        "買賣汽車",
        "中古車買賣"
      ],
      "hashtags": [
        "#汽車租賃",
        "#呂學承"
      ],
      "createdAt": "2025-12-13T16:55:59.178Z",
      "updatedAt": "2025-12-13T16:55:59.178Z",
      "category": "",
      "editCount": 1
    }
  ]
}